sonnerrise_web/__init__.py
sonnerrise_web/app.py
sonnerrise_web/cli.py
sonnerrise_web/forms.py
sonnerrise_web/views/__init__.py
sonnerrise_web/views/calendar.py
sonnerrise_web/views/definitions.py
sonnerrise_web/views/home.py
sonnerrise_web/views/personas.py
sonnerrise_web/views/promo.py
sonnerrise_web/views/tools.py
sonnerrise_web/views/tracks.py
sonnerrise_web-0.1.0.dist-info/METADATA
sonnerrise_web-0.1.0.dist-info/WHEEL
sonnerrise_web-0.1.0.dist-info/entry_points.txt
sonnerrise_web-0.1.0.dist-info/top_level.txt
sonnerrise_web-0.1.0.dist-info/RECORD
