Metadata-Version: 2.4
Name: sonnerrise-web
Version: 0.1.0
Summary: Flask web interface for Sonnerrise
Author-email: Konstantin Boyandin <developer@boyandin.com>
License: MIT
Requires-Python: >=3.11
Requires-Dist: flask>=3.0.0
Requires-Dist: flask-wtf>=1.2.0
Requires-Dist: wtforms>=3.1.0
Requires-Dist: sonnerrise-core
Requires-Dist: sonnerrise-personas
Requires-Dist: sonnerrise-definitions
Requires-Dist: sonnerrise-tracks
Requires-Dist: sonnerrise-promo
Requires-Dist: sonnerrise-calendar
Requires-Dist: sonnerrise-tools
Provides-Extra: dev
Requires-Dist: pytest>=7.0.0; extra == "dev"
Requires-Dist: pytest-cov>=4.0.0; extra == "dev"
